easypeasy/__init__.py
easypeasy-0.0.0.dist-info/LICENSE
easypeasy-0.0.0.dist-info/METADATA
easypeasy-0.0.0.dist-info/WHEEL
easypeasy-0.0.0.dist-info/top_level.txt
easypeasy-0.0.0.dist-info/RECORD
