Metadata-Version: 2.1
Name: easypeasy
Version: 0.0.0
Summary: Old fashioned and fluid API for engineering & data science general purpose
Author-email: RandomCraftr <contact.randomcraftr@gmail.com>
License: MIT License        
Project-URL: Homepage, https://github.com/RandomCraftr/easypeasy
Project-URL: Bug Tracker, https://github.com/RandomCraftr/easypeasy/issues
Classifier: Programming Language :: Python :: 3
Classifier: License :: OSI Approved :: MIT License
Classifier: Operating System :: OS Independent
Requires-Python: >=3.9
License-File: LICENSE
